boolopt.py
boolopt-1.1.dist-info/DESCRIPTION.rst
boolopt-1.1.dist-info/METADATA
boolopt-1.1.dist-info/RECORD
boolopt-1.1.dist-info/WHEEL
boolopt-1.1.dist-info/metadata.json
boolopt-1.1.dist-info/top_level.txt
