Metadata-Version: 2.0
Name: boolopt
Version: 1.1
Summary: Boolean expression minimizer
Home-page: http://www.weaselhat.com/boolopt/
Author: Michael Greenberg
Author-email: mike@weaselhat.com
License: UNKNOWN
Platform: UNKNOWN
